neowise/__init__.py
neowise/activations.py
neowise/cost_function.py
neowise/functional.py
neowise/layers.py
neowise/neural_net.py
neowise/optimizers.py
neowise/plots.py
neowise/regularizers.py
neowise-0.1.0.dist-info/LICENSE.md
neowise-0.1.0.dist-info/METADATA
neowise-0.1.0.dist-info/WHEEL
neowise-0.1.0.dist-info/top_level.txt
neowise-0.1.0.dist-info/RECORD
