Metadata-Version: 2.1
Name: neowise
Version: 0.1.0
Summary: A Deep Learning library built from scratch using Python and NumPy
Home-page: https://github.com/pranavsastry/neowise
Author: Pranav Sastry
Author-email: pranava.sri@gmail.com
Maintainer: Pranav Sastry
License: UNKNOWN
Platform: UNKNOWN
Classifier: Programming Language :: Python :: 3
Classifier: License :: OSI Approved :: MIT License
Requires-Dist: numpy
Requires-Dist: matplotlib
Requires-Dist: hdfdict
Requires-Dist: prettytable
Requires-Dist: tqdm
